llama_index/readers/gcs/__init__.py
llama_index/readers/gcs/base.py
llama_index_readers_gcs-0.5.1.dist-info/METADATA
llama_index_readers_gcs-0.5.1.dist-info/WHEEL
llama_index_readers_gcs-0.5.1.dist-info/licenses/LICENSE
llama_index_readers_gcs-0.5.1.dist-info/RECORD
