Metadata-Version: 2.4
Name: llama-index-readers-gcs
Version: 0.5.1
Summary: llama-index readers gcs integration
Author-email: Your Name <you@example.com>
Maintainer: nfiacco
License-Expression: MIT
License-File: LICENSE
Keywords: bucket,gcp,gcs,google cloud storage
Requires-Python: <4.0,>=3.9
Requires-Dist: gcsfs<2026,>=2024.0.0
Requires-Dist: llama-index-core<0.15,>=0.13.0
Requires-Dist: llama-index-readers-file<0.6,>=0.5.0
